{"_type":"export","__export_format":4,"__export_date":"2024-12-05T02:23:42.180Z","__export_source":"insomnia.desktop.app:v10.2.0","resources":[{"_id":"req_36a4b184ef2f4480afd6a5d29a99d5a4","parentId":"fld_0fc5c816acff48ffa0b8343e1f6cded3","modified":1733364431678,"created":1733355844637,"url":"http://localhost:8080/kits/1","name":"Excluir Kit","description":"","method":"DELETE","body":{},"parameters":[],"headers":[{"id":"pair_8697bf6678db415a97a7f5844167bcae","name":"Content-Type","value":"application/json","description":"","disabled":false}],"authentication":{},"metaSortKey":-1733355844637,"isPrivate":false,"settingStoreCookies":true,"settingSendCookies":true,"settingDisableRenderRequestBody":false,"settingEncodeUrl":true,"settingRebuildPath":true,"settingFollowRedirects":"global","_type":"request"},{"_id":"fld_0fc5c816acff48ffa0b8343e1f6cded3","parentId":"wrk_a06e36fc467a4f9ebd51fc319c9c0e13","modified":1733355844615,"created":1733355844615,"name":"Kits","description":"","environment":{},"environmentPropertyOrder":null,"metaSortKey":-1733355844615,"_type":"request_group"},{"_id":"wrk_a06e36fc467a4f9ebd51fc319c9c0e13","parentId":null,"modified":1733355844607,"created":1733355844607,"name":"ProjetoFinalN3","description":"","scope":"collection","_type":"workspace"},{"_id":"req_9bac53b3ded343d9add3263c694c6d75","parentId":"fld_0fc5c816acff48ffa0b8343e1f6cded3","modified":1733364427897,"created":1733355844635,"url":"http://localhost:8080/kits/1","name":"Atualizar Kit","description":"","method":"PUT","body":{"mimeType":"application/json","text":"{\n  \"codigo\": \"KIT001\",\n  \"descricao\": \"Kit de Ferramentas Atualizado\",\n  \"precoVenda\": 175.00,\n  \"estruturaKit\": []\n}"},"parameters":[],"headers":[{"id":"pair_5d8d85c6da484f1cadc55a45619f0238","name":"Content-Type","value":"application/json","description":"","disabled":false}],"authentication":{},"metaSortKey":-1733355844635,"isPrivate":false,"settingStoreCookies":true,"settingSendCookies":true,"settingDisableRenderRequestBody":false,"settingEncodeUrl":true,"settingRebuildPath":true,"settingFollowRedirects":"global","_type":"request"},{"_id":"req_12915b2bd8ea442ba64f29eadf401957","parentId":"fld_0fc5c816acff48ffa0b8343e1f6cded3","modified":1733364424619,"created":1733355844634,"url":"http://localhost:8080/kits","name":"Listar Kits","description":"","method":"GET","body":{},"parameters":[],"headers":[{"id":"pair_38eb9c53f2394d3d9e7076cd55c1b92b","name":"Content-Type","value":"application/json","description":"","disabled":false}],"authentication":{},"metaSortKey":-1733355844634,"isPrivate":false,"settingStoreCookies":true,"settingSendCookies":true,"settingDisableRenderRequestBody":false,"settingEncodeUrl":true,"settingRebuildPath":true,"settingFollowRedirects":"global","_type":"request"},{"_id":"req_ea00589c39b243e5989829149550aa39","parentId":"fld_0fc5c816acff48ffa0b8343e1f6cded3","modified":1733364420981,"created":1733355844631,"url":"http://localhost:8080/kits","name":"Criar Kit","description":"","method":"POST","body":{"mimeType":"application/json","text":"{\n  \"codigo\": \"KIT001\",\n  \"descricao\": \"Kit de Ferramentas\",\n  \"precoVenda\": 150.00,\n  \"estruturaKit\": []\n}"},"parameters":[],"headers":[{"id":"pair_fb1675fa94ca449e936c496ed0b9c53f","name":"Content-Type","value":"application/json","description":"","disabled":false}],"authentication":{},"metaSortKey":-1733355844631,"isPrivate":false,"settingStoreCookies":true,"settingSendCookies":true,"settingDisableRenderRequestBody":false,"settingEncodeUrl":true,"settingRebuildPath":true,"settingFollowRedirects":"global","_type":"request"},{"_id":"req_da391809a2214bd1ab6400ff1621abf3","parentId":"fld_f7bc1239de544ea59cc13cc782c9f719","modified":1733364416614,"created":1733355844629,"url":"http://localhost:8080/produtos/1","name":"Excluir Produto","description":"","method":"DELETE","body":{},"parameters":[],"headers":[{"id":"pair_9674c10139d4404da8fe9003e0cd4dd5","name":"Content-Type","value":"application/json","description":"","disabled":false}],"authentication":{},"metaSortKey":-1733355844629,"isPrivate":false,"settingStoreCookies":true,"settingSendCookies":true,"settingDisableRenderRequestBody":false,"settingEncodeUrl":true,"settingRebuildPath":true,"settingFollowRedirects":"global","_type":"request"},{"_id":"fld_f7bc1239de544ea59cc13cc782c9f719","parentId":"wrk_a06e36fc467a4f9ebd51fc319c9c0e13","modified":1733355844613,"created":1733355844613,"name":"Produtos","description":"","environment":{},"environmentPropertyOrder":null,"metaSortKey":-1733355844613,"_type":"request_group"},{"_id":"req_71270bffc46a47b7ae8b31e970549da5","parentId":"fld_f7bc1239de544ea59cc13cc782c9f719","modified":1733364412731,"created":1733355844628,"url":"http://localhost:8080/produtos/1","name":"Atualizar Produto","description":"","method":"PUT","body":{"mimeType":"application/json","text":"{\n  \"codigo\": \"PROD001\",\n  \"descricao\": \"Produto Final Atualizado\",\n  \"unidadeMedida\": \"PC\",\n  \"preco\": 55.00,\n  \"precoVenda\": 80.00,\n  \"tipo\": \"PE\",\n  \"estruturaPadrao\": []\n}"},"parameters":[],"headers":[{"id":"pair_68882be7a97e411e80921a85df715f6f","name":"Content-Type","value":"application/json","description":"","disabled":false}],"authentication":{},"metaSortKey":-1733355844628,"isPrivate":false,"settingStoreCookies":true,"settingSendCookies":true,"settingDisableRenderRequestBody":false,"settingEncodeUrl":true,"settingRebuildPath":true,"settingFollowRedirects":"global","_type":"request"},{"_id":"req_ce253a6fa24944a3ac9e5d75377f4d86","parentId":"fld_f7bc1239de544ea59cc13cc782c9f719","modified":1733364408326,"created":1733355844627,"url":"http://localhost:8080/produtos","name":"Listar Produtos","description":"","method":"GET","body":{},"parameters":[],"headers":[{"id":"pair_4e7f9e288c594bbfbed9f32af3a30d5c","name":"Content-Type","value":"application/json","description":"","disabled":false}],"authentication":{},"metaSortKey":-1733355844627,"isPrivate":false,"settingStoreCookies":true,"settingSendCookies":true,"settingDisableRenderRequestBody":false,"settingEncodeUrl":true,"settingRebuildPath":true,"settingFollowRedirects":"global","_type":"request"},{"_id":"req_612548f90b5f454cba2a057dad328371","parentId":"fld_f7bc1239de544ea59cc13cc782c9f719","modified":1733364706131,"created":1733355844624,"url":"http://localhost:8080/produtos","name":"Criar Produto","description":"","method":"POST","body":{"mimeType":"application/json","text":"{\n  \"codigo\": \"PROD001\",\n  \"descricao\": \"Produto Final\",\n  \"unidadeMedida\": \"PC\",\n  \"preco\": 50.00,\n  \"precoVenda\": 75.00,\n  \"tipo\": \"PE\",\n  \"estruturaPadrao\": []\n}"},"parameters":[],"headers":[{"id":"pair_28ce42f844074c3090466e716e8cc9bf","name":"Content-Type","value":"application/json","description":"","disabled":false}],"authentication":{},"metaSortKey":-1733355844624,"isPrivate":false,"settingStoreCookies":true,"settingSendCookies":true,"settingDisableRenderRequestBody":false,"settingEncodeUrl":true,"settingRebuildPath":true,"settingFollowRedirects":"global","_type":"request"},{"_id":"req_a518db8ed0a24e09a7fbd51801811094","parentId":"fld_9518be2fe09c4766b7bb5658bd7ae183","modified":1733364260313,"created":1733355844622,"url":"http://localhost:8080/insumos/1","name":"Excluir Insumo","description":"","method":"DELETE","body":{},"parameters":[],"headers":[{"id":"pair_f42adbb1807b4a6d99f22debcd0ef5c0","name":"Content-Type","value":"application/json","description":"","disabled":false}],"authentication":{},"metaSortKey":-1733355844622,"isPrivate":false,"settingStoreCookies":true,"settingSendCookies":true,"settingDisableRenderRequestBody":false,"settingEncodeUrl":true,"settingRebuildPath":true,"settingFollowRedirects":"global","_type":"request"},{"_id":"fld_9518be2fe09c4766b7bb5658bd7ae183","parentId":"wrk_a06e36fc467a4f9ebd51fc319c9c0e13","modified":1733355844608,"created":1733355844608,"name":"Insumos","description":"","environment":{},"environmentPropertyOrder":null,"metaSortKey":-1733355844612,"_type":"request_group"},{"_id":"req_56b706e1af0149dca29af8fd72ff0f55","parentId":"fld_9518be2fe09c4766b7bb5658bd7ae183","modified":1733364358670,"created":1733355844621,"url":"http://localhost:8080/insumos/1","name":"Atualizar Insumo","description":"","method":"PUT","body":{"mimeType":"application/json","text":"{\n  \"codigo\": \"INS001\",\n  \"descricao\": \"Parafuso Atualizado\",\n  \"unidadeMedida\": \"PC\",\n  \"fornecedor\": \"Fornecedor A\",\n  \"preco\": 2\n}"},"parameters":[],"headers":[{"id":"pair_3c57a9cd16fb4940a4fad94506e37ab9","name":"Content-Type","value":"application/json","description":"","disabled":false}],"authentication":{},"metaSortKey":-1733355844621,"isPrivate":false,"settingStoreCookies":true,"settingSendCookies":true,"settingDisableRenderRequestBody":false,"settingEncodeUrl":true,"settingRebuildPath":true,"settingFollowRedirects":"global","_type":"request"},{"_id":"req_d4dab37e0008483b9dad11e1f2596fd5","parentId":"fld_9518be2fe09c4766b7bb5658bd7ae183","modified":1733364251558,"created":1733355844620,"url":"http://localhost:8080/insumos","name":"Listar Insumos","description":"","method":"GET","body":{},"parameters":[],"headers":[{"id":"pair_4b3bc2f4181e42bdb22cea1acf2ac108","name":"Content-Type","value":"application/json","description":"","disabled":false}],"authentication":{},"metaSortKey":-1733355844620,"isPrivate":false,"settingStoreCookies":true,"settingSendCookies":true,"settingDisableRenderRequestBody":false,"settingEncodeUrl":true,"settingRebuildPath":true,"settingFollowRedirects":"global","_type":"request"},{"_id":"req_0c15e63ab5fb45f98aa1a358b0c73809","parentId":"fld_9518be2fe09c4766b7bb5658bd7ae183","modified":1733363925852,"created":1733355844617,"url":"http://localhost:8080/insumos","name":"Criar Insumo","description":"","method":"POST","body":{"mimeType":"application/json","text":"{\n  \"codigo\": \"INS001\",\n  \"descricao\": \"Parafuso\",\n  \"unidadeMedida\": \"PC\",\n  \"fornecedor\": \"Fornecedor A\",\n  \"preco\": 1.50\n}"},"parameters":[],"headers":[{"id":"pair_b8ebff1901744bccb6857c5866aee04c","name":"Content-Type","value":"application/json","description":"","disabled":false}],"authentication":{},"metaSortKey":-1733355844617,"isPrivate":false,"settingStoreCookies":true,"settingSendCookies":true,"settingDisableRenderRequestBody":false,"settingEncodeUrl":true,"settingRebuildPath":true,"settingFollowRedirects":"global","_type":"request"},{"_id":"env_edf0c8267ec440ed7118a952f0f456615aa9cab3","parentId":"wrk_a06e36fc467a4f9ebd51fc319c9c0e13","modified":1733355846134,"created":1733355846134,"name":"Base Environment","data":{},"dataPropertyOrder":null,"color":null,"isPrivate":false,"metaSortKey":1733355846134,"_type":"environment"},{"_id":"jar_edf0c8267ec440ed7118a952f0f456615aa9cab3","parentId":"wrk_a06e36fc467a4f9ebd51fc319c9c0e13","modified":1733355846137,"created":1733355846137,"name":"Default Jar","cookies":[],"_type":"cookie_jar"}]}